{
  "id": "B007",
  "leaflet_section": "심한장애(중증)/심하지 않은 장애(경증) 전국공통",
  "leaflet_number": 7,
  "title": "고속도로 통행료 50% 할인",
  "short_summary": "고속도로통행료 50% 할인 (배기량 2000cc이하 승용차, 7~10인승 승용차, 12인승이하 승합차, 1톤이하 화물차) (전단지 원문)",
  "category": "교통",
  "benefit_type": "할인",
  "supported_amount": {
    "rate": "50%",
    "amount": null,
    "scope": "한국도로공사가 관리하는 재정 고속도로(경부·중부·서해안 등 약 30여 개 노선)와 민자고속도로(인천공항·천안논산·서울외곽순환 등 대부분의 민자노선) 전 구간 통행료의 50%. 통행료 본요금 + 첨두시간 할증분 모두 50% 감면. 단, 본 감면은 다른 할인(출퇴근 시간대 할인 20%/50%, 명절 면제, 화물차 야간할인, 친환경차 할인 등)과 중복 적용되지 않으며, 가장 유리한 할인 1종만 자동 적용됨."
  },
  "eligibility": {
    "target": "「장애인복지법」에 따라 등록된 장애인 본인 또는 같은 세대의 보호자(주민등록표상 함께 등재된 직계존비속·배우자·형제자매 등)가 소유하거나 1년 이상 임차·대여한 비영업용 자동차 1대",
    "severity_levels": ["심한 장애(중증)", "심하지 않은 장애(경증)"],
    "companion_allowed": null,
    "income_criteria": null,
    "age_criteria": null,
    "residency_criteria": "전국. 단, 차량 운행 시 등록 장애인 본인이 탑승해야 함(본인 운전 또는 보호자 운전에 동승). 미탑승 단독 운행 시 감면 무효이며 부정사용으로 사후 추징될 수 있음."
  },
  "legal_basis": [
    {
      "name": "장애인복지법",
      "article": "제30조(경제적 부담의 경감)",
      "url": "https://www.law.go.kr/법령/장애인복지법"
    },
    {
      "name": "장애인복지법 시행령",
      "article": "제17조 및 별표2(공공시설 등의 이용요금 감면 기준)",
      "url": "https://www.law.go.kr/법령/장애인복지법시행령"
    },
    {
      "name": "유료도로법",
      "article": "제15조(통행료의 감면)",
      "url": "https://www.law.go.kr/법령/유료도로법"
    },
    {
      "name": "유료도로법 시행령",
      "article": "제8조(통행료의 감면 대상 등) 및 별표",
      "url": "https://www.law.go.kr/법령/유료도로법시행령"
    },
    {
      "name": "유료도로법 시행규칙",
      "article": "통행료 감면 신청 절차",
      "url": "https://www.law.go.kr/법령/유료도로법시행규칙"
    }
  ],
  "operating_agencies": [
    {
      "region": "전국(재정 고속도로)",
      "agency": "한국도로공사",
      "lines_or_routes": ["경부고속도로", "중부·중부내륙·중앙·영동·서해안·남해·호남·통영대전·당진영덕·서울양양 등 한국도로공사 관리 전 노선"],
      "apply_channel": "(1) 주소지 동주민센터에서 통합복지카드(A형, 고속도로 감면 기능 포함) 발급 → (2) 감면단말기 또는 일반 하이패스 단말기 구입 → (3) hipass.co.kr 또는 동주민센터에서 사전등록(차량번호·단말기 일련번호·지문 또는 휴대폰 위치 동의) → (4) 톨게이트 통과",
      "card_or_proof_type": "통합복지카드 A형(고속도로 감면 기능), 감면하이패스 단말기(지문형/일반형), 또는 일반 톨게이트 통과 시 장애인자동차표지+통합복지카드 제시",
      "url": "https://www.ex.co.kr/",
      "notes": "한국도로공사는 2022년 11월부터 '일반 하이패스 단말기 + 휴대폰 위치확인' 방식 감면도 도입. 사전 동의한 휴대폰의 위치를 톨게이트 통과 시점에 조회해 본인 탑승 여부를 자동 확인."
    },
    {
      "region": "전국(민자고속도로)",
      "agency": "민자고속도로 운영사(천안논산고속도로(주), 신공항하이웨이(주), 서울외곽순환(주), 서수원-의왕 고속도로, 서울-춘천고속도로, 부산울산고속도로 등 약 20여 개사)",
      "lines_or_routes": ["인천국제공항고속도로", "천안논산고속도로", "대구부산고속도로", "서울외곽순환고속도로", "서울-춘천고속도로", "부산울산고속도로", "서수원-의왕고속도로", "광주-원주(제2영동)", "옥산-오창 등 민자노선 전반"],
      "apply_channel": "한국도로공사 발급 통합복지카드 + 감면단말기로 동일하게 통과. 별도 등록 없음(민자도로도 동일 감면 시스템 연동).",
      "card_or_proof_type": "통합복지카드 A형, 감면하이패스 단말기, 장애인자동차표지",
      "url": "https://cephis.koti.re.kr/",
      "notes": "민자고속도로 감면비용은 운영사가 실시협약에 따라 자체 부담(국토부 협의). 일부 민자노선은 일반 톨게이트에서 통합복지카드 미인식 시 매표창구에서 표지+등록증 제시 후 수동 감면 처리."
    }
  ],
  "how_to_use": {
    "default": "방법(1) 하이패스 통과: 통합복지카드 A형을 감면단말기에 삽입(또는 일반 단말기에 삽입+휴대폰 위치 동의)하고 하이패스 차로 통과. 방법(2) 일반차로 통과: 톨게이트 정산 창구에서 통합복지카드와 장애인자동차표지를 함께 제시하면 50% 차감 정산.",
    "with_card": "감면하이패스 단말기 사용 시: 출발 전 지문인식기에 본인 지문 인증(지문형) 또는 사전 동의된 휴대폰 소지(일반형)로 본인 탑승 자동 확인 → 하이패스 차로 무정차 통과 → 통행료 50% 자동 차감. 신용형 통합복지카드는 후불 청구, 충전형/체크형은 즉시 차감.",
    "without_card": "통합복지카드 미발급 시: 일반 톨게이트 정산창구에서 장애인자동차표지(주차가능/주차불가 무관)와 장애인등록증을 제시하면 현장 50% 감면 정산 가능. 단, 표지 부착 차량에 본인이 실제로 탑승했음을 확인할 수 있어야 함.",
    "exceptions": "출퇴근 시간대 할인(평일 05-07/20-22시 50%, 07-09/18-20시 20%), 명절 면제, 화물차 야간할인, 친환경차(전기/수소) 감면 등 다른 할인과 중복 적용 불가. 시스템이 가장 유리한 1종만 자동 적용. 영업용(택시·렌터카 사업용 등)은 감면 제외(단 본인이 1년 이상 임차·대여한 차량은 2024년 개정으로 감면 대상에 포함됨)."
  },
  "application": {
    "where": [
      { "channel": "주소지 동주민센터(통합복지카드 A형 신청)", "method": "방문", "url": "https://www.gov.kr/" },
      { "channel": "고속도로통행료 홈페이지(하이패스 감면 사전등록)", "method": "온라인", "url": "https://www.hipass.co.kr/hipass/reductionAgree.do" },
      { "channel": "한국도로공사 스마트하이패스센터·지역본부·전국 지사(지문등록·단말기 등록)", "method": "방문", "url": "https://www.ex.co.kr/" },
      { "channel": "한국도로공사서비스(주) 영업소", "method": "방문", "url": "https://exservice.co.kr/service/toll_pay.php" },
      { "channel": "관할 보훈(지)청(국가유공자 겸 장애인)", "method": "방문", "url": "https://www.mpva.go.kr/" },
      { "channel": "단말기 제조사 콜센터(엠피온 1544-8202, SD시스템·영윈 1899-3316, 휴먼케어 1688-3017)", "method": "전화", "url": "https://www.humancare.co.kr/bbs/content.php?co_id=process" }
    ],
    "required_documents": [
      "신청서(현장 비치)",
      "신분증(주민등록증·운전면허증 등)",
      "장애인등록증(또는 장애인복지카드)",
      "자동차등록증(본인 또는 동일세대 보호자 명의)",
      "임차·대여 차량의 경우: 1년 이상 임대차계약서 사본",
      "통장 사본(체크/충전형 카드 신청 시)",
      "단말기 일련번호(감면하이패스 등록 시)",
      "지문등록 동의서(지문형 단말기 사용 시)",
      "휴대폰 위치정보 제공 동의서(일반형+위치확인 방식)",
      "대리 신청 시: 위임장, 대리인 신분증"
    ],
    "processing_period": "통합복지카드 A형은 신청 후 약 2~3주(한국조폐공사 발급). 단말기 사전등록은 hipass.co.kr 온라인 신청 시 익일 반영. 지문등록은 동주민센터·도로공사 지사에서 즉시 처리. 단말기 자체 구매는 즉시(제조사 택배 또는 영업점 현장 수령).",
    "fee": {
      "default": "통합복지카드 A형 신규 발급은 무료. 분실·훼손 재발급 약 4,200원. 감면하이패스 단말기 구입비용은 종류에 따라 다름: 일반형 본인부담 3천~3만원(한국도로공사 4만원 지원), 지문형 본인부담 4.2만원(한국도로공사 7만원 지원).",
      "exceptions": "한국도로공사는 감면 일반 단말기 최대 1.9만원, 지문형 최대 4.2만원의 구매비용을 지원(연간 예산 소진 시 지원 종료)."
    },
    "online_available": true,
    "proxy_allowed": true
  },
  "validity": {
    "expiry": "통합복지카드 A형 유효기간은 장애 재판정 기한과 연동(영구 판정자는 별도 만료 없음). 감면하이패스 단말기 사전등록은 등록차량을 매도·폐차하거나 단말기를 교체할 때까지 유효.",
    "renewal": "차량 변경·매도·폐차 시 즉시 hipass.co.kr 또는 한국도로공사 톨게이트 사무실에서 단말기 정보(차량번호) 변경 또는 등록 해지 신청. 카드 분실 시 재발급 → 사전등록 정보도 새 카드로 갱신 필요."
  },
  "exceptions_and_caveats": [
    "감면 대상 차량 요건(전단지 원문): 배기량 2,000cc 이하 승용차 / 승차정원 7~10인승 승용차 / 승차정원 12인승 이하 승합차(배기량 제한 없음) / 최대적재량 1톤 이하 화물차(배기량 제한 없음). 이 4개 유형 중 어느 하나에 해당해야 하며, 그 외 차량(대형 승합·트럭 등)은 감면 대상 아님.",
    "장애인 본인 또는 동일 세대 보호자(주민등록표상 함께 등재) 명의의 비영업용 차량 1대만 등록 가능. 2024년 개정으로 1년 이상 임차·대여한 차량도 추가 인정.",
    "장애인 본인이 실제 탑승해야 감면 적용. 본인 미탑승 운행 시 감면 무효이며, 적발 시 통행료 본요금 및 가산금(통상 10배) 추징.",
    "다른 통행료 할인(출퇴근 시간대, 명절, 화물차 야간, 친환경차 등)과 중복 적용 불가 — 시스템이 가장 유리한 1종만 자동 적용.",
    "감면하이패스 단말기와 통합복지카드(A형)는 반드시 한 쌍으로 사용. 일반 신용카드 하이패스 단말기에 통합복지카드를 끼우면 감면이 적용되지 않거나 부정사용으로 처리될 수 있음.",
    "감면단말기를 사용하지 않고 일반차로(매표창구)로 통과할 경우, 장애인자동차표지+통합복지카드를 함께 제시해야 현장 감면 처리됨. 표지만 제시하고 카드 없이는 50% 감면이 안 되는 톨게이트도 있음.",
    "민자고속도로는 한국도로공사 감면 시스템과 연동되어 동일하게 50% 적용되지만, 일부 노선은 단말기 인식 오류 시 사후 환급 절차가 복잡할 수 있음.",
    "본 항목은 「장애인 자동차 표지」(B010)와 연계 — B010 표지 발급이 사실상 선결 요건. 표지 없이는 일반차로 감면 정산 불가.",
    "사전 동의 없는 휴대폰 위치 미확인 상태에서 일반형 단말기 사용 시 감면 미적용 → hipass.co.kr 사전등록 필수."
  ],
  "penalties_for_misuse": "감면 자격 없는 자가 통합복지카드·감면단말기를 이용해 통행료를 감면받은 경우, 통행료 본요금 및 부가통행료(통상 10배)를 추징(유료도로법 제20조). 통합복지카드를 타인에게 양도·대여 시 카드 정지 및 재발급 1년 제한. 장애인자동차표지를 부정 사용한 경우 「장애인복지법」 제86조에 따라 과태료 200만원, 위조 시 공문서위조 및 위조공문서행사죄로 형사처벌(10년 이하 징역) 가능.",
  "faq": [
    {
      "q": "내 차가 감면 대상인지 어떻게 확인하나요?",
      "a": "다음 4가지 중 하나에 해당하면 됩니다. ①배기량 2,000cc 이하 승용차, ②승차정원 7~10인승 승용차, ③승차정원 12인승 이하 승합차(배기량 무관), ④최대적재량 1톤 이하 화물차(배기량 무관). 자동차등록증의 '배기량'·'승차정원'·'최대적재량' 항목으로 확인하세요. 본인 또는 같은 세대 보호자 명의(또는 1년 이상 임차·대여)의 비영업용 차량 1대만 등록 가능합니다."
    },
    {
      "q": "어떻게 신청하나요? 단말기는 꼭 필요한가요?",
      "a": "단말기 없이도 가능합니다. ①주소지 동주민센터에서 '통합복지카드 A형'(고속도로 감면 기능 포함)을 신청 → ②톨게이트 일반차로에서 카드+장애인자동차표지 제시로 50% 감면. 하이패스를 무정차로 이용하려면 추가로 ③감면하이패스 단말기 구매 → ④hipass.co.kr 또는 동주민센터에서 사전등록(차량·지문 또는 휴대폰 위치 동의) → ⑤하이패스 차로 통과. 한국도로공사가 단말기 구입비를 일반형 최대 1.9만원, 지문형 최대 4.2만원 지원합니다."
    },
    {
      "q": "감면단말기는 어디서 사나요? 가격은요?",
      "a": "제조사 콜센터 또는 영업점에서 직접 구매합니다. 일반형은 엠피온(1544-8202), SD시스템·영윈(1899-3316), 지문형은 휴먼케어(1688-3017). 본인부담 가격은 일반형 3천~3만원, 지문형 4.2만원(한국도로공사 지원 후 차액). 카드형 단말기(통합복지카드 삽입형)는 일반 시중 단말기 대비 약간 비쌉니다."
    },
    {
      "q": "지문 인증이 꼭 필요한가요?",
      "a": "꼭 그렇지는 않습니다. 2022년 11월 한국도로공사가 도입한 '일반 하이패스 단말기 + 휴대폰 위치확인' 방식을 사용하면 지문 등록 없이도 감면받을 수 있습니다. hipass.co.kr에서 휴대폰 번호·위치정보 제공에 동의하면, 톨게이트 통과 시점에 통신사 위치 조회로 본인 탑승 여부를 자동 확인합니다. 다만 휴대폰을 켜지 않거나 위치 동의를 철회하면 감면이 안 됩니다. 지문형은 본인이 운전·동승할 때 매번 지문 인증을 해야 합니다."
    },
    {
      "q": "본인이 안 타고 가족이 혼자 운전해도 50% 할인되나요?",
      "a": "안 됩니다. 등록 장애인 본인이 실제로 차량에 탑승해야만 감면이 적용됩니다. 본인 미탑승 시 감면은 부정사용으로 간주되며, 적발 시 통행료 본요금과 부가통행료(통상 10배)가 추징됩니다. 휴대폰 위치확인 방식은 통신사 위치로 본인 탑승을 자동 검증하므로, 본인이 안 타면 자동으로 일반요금이 부과됩니다."
    },
    {
      "q": "민자고속도로(인천공항·천안논산 등)에서도 50% 할인되나요?",
      "a": "네. 한국도로공사 감면 시스템과 연동된 거의 모든 민자고속도로(인천공항, 천안논산, 서울외곽순환, 서울-춘천, 부산울산, 서수원-의왕 등 약 20여 개 노선)에서 동일하게 50% 적용됩니다. 단말기 인식이 안 되는 일부 일반차로에서는 톨게이트 직원에게 통합복지카드와 장애인자동차표지를 제시하면 수동 감면 정산됩니다."
    },
    {
      "q": "출퇴근 할인이나 명절 면제와 같이 받을 수 있나요?",
      "a": "중복 적용은 불가합니다. 시스템이 모든 할인 중 가장 유리한 1종만 자동 적용합니다. 예: 출퇴근 시간대 50% 할인 구간을 장애인이 통과하면 둘 다 50%로 동일하므로 한 번만 적용되며, 출퇴근 20% 구간이라면 장애인 50%가 적용됩니다. 명절 면제 기간(설·추석 4일)에는 본 감면 없이도 무료입니다."
    },
    {
      "q": "렌터카·리스 차량도 가능한가요?",
      "a": "2024년 유료도로법 시행령 개정으로 본인 또는 동일 세대 보호자가 '1년 이상 임차·대여한 차량'도 감면 대상에 포함되었습니다. 1년 미만 단기 렌터카는 대상이 아닙니다. 동주민센터 신청 시 1년 이상 임대차계약서 사본을 제출하면 통합복지카드 A형으로 등록 가능합니다."
    },
    {
      "q": "차를 바꿨는데 그대로 사용해도 되나요?",
      "a": "안 됩니다. 차량을 매도·폐차하거나 새 차로 바꾸면 즉시 hipass.co.kr에서 단말기 등록 차량번호를 변경하거나, 한국도로공사 톨게이트 사무실에서 직접 처리해야 합니다. 일부 운전자는 톨게이트 사무실 직접 방문이 불편하다는 민원이 있어 절차 간소화가 추진 중입니다."
    },
    {
      "q": "장애인 자동차표지(B010)가 꼭 있어야 하나요?",
      "a": "통합복지카드 A형으로 하이패스 자동 감면만 받는다면 표지 없이도 작동은 합니다. 그러나 일반차로 톨게이트에서 수동 정산을 받거나 단말기 오류 시 사후 환급을 받으려면 장애인자동차표지(B010)가 필요합니다. 또한 표지는 공영주차장 감면·장애인전용주차구역 이용 등 다른 혜택과도 연결되므로 함께 발급받는 것이 좋습니다."
    },
    {
      "q": "통행료를 일단 다 내고 나중에 환급받을 수 있나요?",
      "a": "원칙적으로는 현장 감면이 원칙이지만, 단말기 오류 등으로 전액이 부과된 경우 한국도로공사 콜센터(1588-2504) 또는 hipass.co.kr 통행료 미환급 메뉴를 통해 사후 환급 신청이 가능합니다. 영수증·통행기록·통합복지카드 정보가 필요합니다."
    },
    {
      "q": "분실하거나 도난당하면 어떻게 하나요?",
      "a": "통합복지카드를 분실하면 즉시 발급 은행 콜센터(신한카드 1544-7000 등)에 분실 신고하고, 동주민센터에서 재발급을 신청하세요. 감면하이패스 단말기 자체가 분실된 경우 hipass.co.kr 또는 한국도로공사 톨게이트 사무실에서 등록 해지 후 새 단말기로 재등록해야 합니다. 분실 신고 전 부정사용분은 본인 책임이 될 수 있습니다."
    }
  ],
  "contact": [
    { "name": "보건복지부 보건복지상담센터", "phone": "129", "url": "https://www.129.go.kr" },
    { "name": "한국도로공사 콜센터", "phone": "1588-2504", "url": "https://www.ex.co.kr/" },
    { "name": "고속도로통행료 홈페이지(하이패스 감면)", "phone": "1588-2504", "url": "https://www.hipass.co.kr/" },
    { "name": "한국도로공사서비스(주)", "phone": "1577-2504", "url": "https://exservice.co.kr/" },
    { "name": "엠피온(주) — 감면 일반 단말기", "phone": "1544-8202", "url": "https://www.mpion.co.kr/" },
    { "name": "(주)에스디시스템 — 감면 일반 단말기", "phone": "1899-3316", "url": null },
    { "name": "(주)영윈 — 감면 일반 단말기", "phone": "1899-3316", "url": null },
    { "name": "(주)휴먼케어 — 감면 지문 단말기", "phone": "1688-3017", "url": "https://www.humancare.co.kr/" },
    { "name": "국토교통부 도로정책과", "phone": "044-201-3893", "url": "https://www.molit.go.kr/" },
    { "name": "민자도로관리지원센터(CEPHIS)", "phone": null, "url": "https://cephis.koti.re.kr/" }
  ],
  "sources": [
    {
      "title": "장애인복지법",
      "publisher": "국가법령정보센터",
      "publisher_type": "법령DB",
      "url": "https://www.law.go.kr/법령/장애인복지법",
      "fallback_url": "https://easylaw.go.kr/CSP/CnpClsMain.laf?popMenu=ov&csmSeq=916&ccfNo=5&cciNo=1&cnpClsNo=1",
      "official_api": {
        "available": true,
        "endpoint": "https://www.law.go.kr/DRF/lawService.do",
        "auth_required": true,
        "docs_url": "https://open.law.go.kr/LSO/main.do"
      },
      "crawl": {
        "frequency": "monthly",
        "change_detection_method": "last_modified_field",
        "css_selector_hint": "법령 본문 상단 '시행일' 표기",
        "robots_txt_ok": true,
        "notes": "국가법령정보 Open API로 안정 모니터링 가능."
      },
      "accessed": "2026-05-19",
      "priority": "primary"
    },
    {
      "title": "장애인복지법 시행령 (별표2 공공시설 등의 이용요금 감면 기준)",
      "publisher": "국가법령정보센터",
      "publisher_type": "법령DB",
      "url": "https://www.law.go.kr/법령/장애인복지법시행령",
      "fallback_url": null,
      "official_api": {
        "available": true,
        "endpoint": "https://www.law.go.kr/DRF/lawService.do",
        "auth_required": true,
        "docs_url": "https://open.law.go.kr/LSO/main.do"
      },
      "crawl": {
        "frequency": "monthly",
        "change_detection_method": "last_modified_field",
        "css_selector_hint": "별표2 표 내용 — 고속도로 통행료 감면 줄",
        "robots_txt_ok": true,
        "notes": null
      },
      "accessed": "2026-05-19",
      "priority": "primary"
    },
    {
      "title": "유료도로법 / 유료도로법 시행령 / 유료도로법 시행규칙",
      "publisher": "국가법령정보센터",
      "publisher_type": "법령DB",
      "url": "https://www.law.go.kr/법령/유료도로법",
      "fallback_url": "https://www.law.go.kr/법령/유료도로법시행령",
      "official_api": {
        "available": true,
        "endpoint": "https://www.law.go.kr/DRF/lawService.do",
        "auth_required": true,
        "docs_url": "https://open.law.go.kr/LSO/main.do"
      },
      "crawl": {
        "frequency": "quarterly",
        "change_detection_method": "last_modified_field",
        "css_selector_hint": "시행령 제8조 통행료 감면 대상",
        "robots_txt_ok": true,
        "notes": "2024년 개정(1년 이상 임차·대여 차량 포함) 추적."
      },
      "accessed": "2026-05-19",
      "priority": "primary"
    },
    {
      "title": "장애인 고속도로 통행료 감면 제도",
      "publisher": "정부24",
      "publisher_type": "중앙정부",
      "url": "https://www.gov.kr/portal/service/serviceInfo/B50000400003",
      "fallback_url": null,
      "official_api": {
        "available": false,
        "endpoint": null,
        "auth_required": null,
        "docs_url": null
      },
      "crawl": {
        "frequency": "quarterly",
        "change_detection_method": "page_hash",
        "css_selector_hint": "본문 영역",
        "robots_txt_ok": true,
        "notes": "민원안내 본문 갱신 시기 점검."
      },
      "accessed": "2026-05-19",
      "priority": "primary"
    },
    {
      "title": "유료 고속도로 통행료 감면 — 찾기쉬운 생활법령정보",
      "publisher": "법제처",
      "publisher_type": "중앙정부",
      "url": "https://easylaw.go.kr/CSP/CnpClsMain.laf?popMenu=ov&csmSeq=916&ccfNo=5&cciNo=1&cnpClsNo=2",
      "fallback_url": null,
      "official_api": {
        "available": false,
        "endpoint": null,
        "auth_required": null,
        "docs_url": null
      },
      "crawl": {
        "frequency": "quarterly",
        "change_detection_method": "page_hash",
        "css_selector_hint": null,
        "robots_txt_ok": true,
        "notes": null
      },
      "accessed": "2026-05-19",
      "priority": "primary"
    },
    {
      "title": "공공요금 감면 — 보건복지부 장애인정책",
      "publisher": "보건복지부",
      "publisher_type": "중앙정부",
      "url": "https://www.mohw.go.kr/menu.es?mid=a10710010500",
      "fallback_url": null,
      "official_api": {
        "available": false,
        "endpoint": null,
        "auth_required": null,
        "docs_url": null
      },
      "crawl": {
        "frequency": "quarterly",
        "change_detection_method": "page_hash",
        "css_selector_hint": "본문 영역 (div#contents 등)",
        "robots_txt_ok": true,
        "notes": "보건복지부 사업안내 책자 동시 모니터링."
      },
      "accessed": "2026-05-19",
      "priority": "primary"
    },
    {
      "title": "통합복지카드 감면 하이패스 신청 / 이용안내",
      "publisher": "한국도로공사(고속도로통행료)",
      "publisher_type": "공기업",
      "url": "https://www.hipass.co.kr/hipass/reductionAgree.do",
      "fallback_url": "https://www.hipass.co.kr/info/guide/05_use_guide_reduction.do",
      "official_api": {
        "available": false,
        "endpoint": null,
        "auth_required": null,
        "docs_url": null
      },
      "crawl": {
        "frequency": "monthly",
        "change_detection_method": "page_hash",
        "css_selector_hint": "본문 영역 — 단말기 종류/지원 금액 안내",
        "robots_txt_ok": true,
        "notes": "단말기 지원 금액·제조사 변경이 잦으므로 monthly."
      },
      "accessed": "2026-05-19",
      "priority": "primary"
    },
    {
      "title": "한국도로공사 메인",
      "publisher": "한국도로공사",
      "publisher_type": "공기업",
      "url": "https://www.ex.co.kr/",
      "fallback_url": "https://exservice.co.kr/service/toll_pay.php",
      "official_api": {
        "available": false,
        "endpoint": null,
        "auth_required": null,
        "docs_url": null
      },
      "crawl": {
        "frequency": "quarterly",
        "change_detection_method": "page_hash",
        "css_selector_hint": null,
        "robots_txt_ok": true,
        "notes": null
      },
      "accessed": "2026-05-19",
      "priority": "secondary"
    },
    {
      "title": "감면하이패스 발급 등록 절차 — 휴먼케어(지문형 단말기)",
      "publisher": "(주)휴먼케어",
      "publisher_type": "민간",
      "url": "https://www.humancare.co.kr/bbs/content.php?co_id=process",
      "fallback_url": null,
      "official_api": {
        "available": false,
        "endpoint": null,
        "auth_required": null,
        "docs_url": null
      },
      "crawl": {
        "frequency": "quarterly",
        "change_detection_method": "page_hash",
        "css_selector_hint": null,
        "robots_txt_ok": true,
        "notes": "지문형 단말기 발급 절차 1차 안내."
      },
      "accessed": "2026-05-19",
      "priority": "secondary"
    },
    {
      "title": "장애인관련 이용안내 — 천안논산고속도로",
      "publisher": "천안논산고속도로(주)",
      "publisher_type": "민간",
      "url": "https://www.cneway.co.kr/sub/info.do?m=0309",
      "fallback_url": null,
      "official_api": {
        "available": false,
        "endpoint": null,
        "auth_required": null,
        "docs_url": null
      },
      "crawl": {
        "frequency": "quarterly",
        "change_detection_method": "page_hash",
        "css_selector_hint": null,
        "robots_txt_ok": true,
        "notes": "민자고속도로 감면 안내 대표 페이지로 사용."
      },
      "accessed": "2026-05-19",
      "priority": "secondary"
    },
    {
      "title": "민자도로관리지원센터(CEPHIS)",
      "publisher": "한국교통연구원",
      "publisher_type": "공기업",
      "url": "https://cephis.koti.re.kr/",
      "fallback_url": null,
      "official_api": {
        "available": false,
        "endpoint": null,
        "auth_required": null,
        "docs_url": null
      },
      "crawl": {
        "frequency": "quarterly",
        "change_detection_method": "page_hash",
        "css_selector_hint": null,
        "robots_txt_ok": true,
        "notes": "민자고속도로 운영사 현황 추적."
      },
      "accessed": "2026-05-19",
      "priority": "supplementary"
    },
    {
      "title": "고속도로 통행료 50% 할인 — 복지뱅크",
      "publisher": "한국사회보장정보원",
      "publisher_type": "공기업",
      "url": "https://www.bokjibank.or.kr/bokji/view.php?zipEncode=2GJn90wDU91DLLMDMetpSfMvWLME",
      "fallback_url": null,
      "official_api": {
        "available": false,
        "endpoint": null,
        "auth_required": null,
        "docs_url": null
      },
      "crawl": {
        "frequency": "quarterly",
        "change_detection_method": "page_hash",
        "css_selector_hint": null,
        "robots_txt_ok": true,
        "notes": null
      },
      "accessed": "2026-05-19",
      "priority": "supplementary"
    },
    {
      "title": "장애인·유공자 1년 이상 임차·대여 차량 감면 확대(보도자료)",
      "publisher": "대한민국 정책브리핑",
      "publisher_type": "중앙정부",
      "url": "https://www.korea.kr/news/policyNewsView.do?newsId=148955704",
      "fallback_url": "https://www.molit.go.kr/USR/NEWS/m_71/dtl.jsp?lcmspage=1&id=95087073",
      "official_api": {
        "available": false,
        "endpoint": null,
        "auth_required": null,
        "docs_url": null
      },
      "crawl": {
        "frequency": "on_demand",
        "change_detection_method": "manual_review",
        "css_selector_hint": null,
        "robots_txt_ok": true,
        "notes": "유료도로법 시행령 개정 보도자료(2024). 시행령 본문이 1차 근거이지만 변경 시점 파악용."
      },
      "accessed": "2026-05-19",
      "priority": "supplementary"
    }
  ],
  "related_items": ["B010", "B008", "B009"],
  "last_verified": "2026-05-19",
  "version": "1.0.0"
}
